{
  "basics": {
    "name": "Mirabela Medallon",
    "label": "Student",
    "picture": "/../images/b4.JPG",
    "email": "",
    "phone": "",
    "website": "https://miraabela.github.io",
    "summary": "I am studying for a B.S. in Computer Science in the Department of Information and Computer Sciences at the University of Hawaii. I expect to graduate in Fall, 2020.",
    "location": {
      "address": "",
      "postalCode": "96816",
      "city": "Honolulu",
      "countryCode": "USA",
      "region": "Hawaii"
    },
    "profiles": [
      {
        "network": "github",
        "username": "miraabela",
        "url": "https://github.com/miraabela"
      },
      {
        "network": "linkedin",
        "username": "mirabela-m-38702b164",
        "url": "https://www.linkedin.com/in/mirabela-m-38702b164/"
      },
      {
        "network": "portfolio",
        "username": "",
        "url": "https://mirabela.carbonmade.com/"
      },
      {
        "network": "instagram",
        "username": "miraabela",
        "url": "https://www.instagram.com/miraabela/"
      }
    ]
  },
  "interests": [
    {
      "name": "web development",
      "keywords": [
      ]
    },
    {
      "name": "sustainability",
      "keywords": [
        "green",
        "climate change",
        "environment",
        "renewable energy"
      ]
    },
    {
      "name": "art, graphic design & photography",
      "keywords": [
        "UI / UX design",
        "adobe",
        "photoshop",
        "illustrator",
        "lightroom",
      ]
    }
  ],
  "skills": [
    {
      "name": "Languages and Frameworks",
      "level": "",
      "keywords": [
        "C",
        "C++",
        "Java",
        "Javascript",
        "HTML & CSS",
        "C#",
        "Arduino"
      ]
    },
    {
      "name": "Toolsets/OS",
      "level": "",
      "keywords": [
        "MacOS",
        "Unity",
        "Wordpress",
        "Adobe Creative Cloud",
        "Linux/Unix shell",
        "VIM"
      ]
    }
  ],
  "education": [
    {
      "institution": "University of Hawaii, Honolulu, HI",
      "area": "Computer Science (expected Fall, 2020)",
      "studyType": "B.S.",
      "startDate": "2016-09-01",
      "endDate": "Present",
      "gpa": "",
      "courses": [
      ]
    }
  ],
  "work": [
    {
      "company": "STEM Center at Kapiolani CC",
      "position": "Web & Graphic Designer",
      "website": "",
      "startDate": "2018-08-15",
      "endDate": "Present",
      "summary": "Currently Redesigning a New Website",
      "highlights": [
        "Designed a new easier system for Tutors/Students to view their work/tutoring schedule",
        "Design appealing recruitment & marketing materials for KCC STEM",
        "Updating the (outdated) KCC STEM Wordpress website & social media pages",
        "Initiative to improve diversity in STEM by changing to content to be more appealing to underrepresented minorities",
      ]
    },
    {
      "company": "STEM Center at Kapiolani CC",
      "position": "Computer Science Tutor",
      "website": "",
      "startDate": "2018-01-15",
      "endDate": "2018-05-15",
      "summary": "Supportive Tutor for ICS Students",
      "highlights": [
        "Tutor / Peer mentor for classes ICS 111, ICS 141, ICS 211 ",
        "Adjust to student’s pace of learning and needs",
        "Actively problem solve and lead students to fix their programs",
        "Assist students with Java Programming & Discrete Math assignments"
      ]
    },
    {
      "company": "Ka Manao Magazine at Leeward CC",
      "position": "Graphic Designer & Photographer",
      "website": "https://issuu.com/kamanaoleeward/docs/winter_2017_master_document_",
      "startDate": "2017-08-15",
      "endDate": "2017-12-15",
      "summary": "Create Clean and Appealing Page Layouts",
      "highlights": [
        "Created new design for Staff Photos for the Winter 17 Issue"
      ]
    },
    {
      "company": "Amaxima Realty and Property Management Group, LLC",
      "position": "Marketing Assistant & Photographer",
      "website": "",
      "startDate": "2016-06-15",
      "endDate": "2017-07-15",
      "summary": "Helped Market and Sell Homes in Las Vegas",
      "highlights": [
        "Capture professional, aesthetically pleasing interior and exterior photos of the properties using a DSLR, tripod, and wide angle lens",
        "Designing print-ready marketing materials such as business cards, flyers, and presentations",
        "Searching for properties on the MLS, uploading property photos to the MLS listing",
        "Providing basic training on computer software use"
      ]
    },
    {
      "company": "Self Employed",
      "position": "Freelance Graphic Designer",
      "website": "https://mirabela.carbonmade.com/",
      "startDate": "2016-06-15",
      "endDate": "2017-07-15",
      "summary": "Designed the Logos of 6 startups",
      "highlights": [
        "Graphic Design Contests: Won those 6, was a runner up in 10.",
        "Communicating with clients to fully understand the brand goals, target audience, and artistic needs",
        "Using various forms of art media and computer software (Adobe) to create memorable and visually impactful logos",
        "Preparing design files for print and web in vector and raster format"
      ]
    }
  ],
  "volunteer": [
    {
      "organization": "St Elizabeth Church Aiea",
      "website": "",
      "position": "Piano Player",
      "startDate": "2018-01-15",
      "endDate": "2018-05-15",
      "summary": "Volunteer piano player for Catholic church",
      "highlights": [
        "Played piano for masses and occasional prayer nights"
      ]
    },
    {
      "organization": "Malaya Elementary School in Rizal, Philippines",
      "website": "",
      "position": "Food & Supply Distributor",
      "startDate": "2017-08-01",
      "endDate": "2017-08-01",
      "summary": "Volunteer in Day Mission in the Philippines",
      "highlights": [
        "Distributed lunch meals and school supplies to children in Malaya Elementary School in Rizal, Philippines."
      ]
    },
    {
      "organization": "AFCEA Hawaii",
      "website": "",
      "position": "Volunteer",
      "startDate": "2018-11-12",
      "endDate": "2017-11-13",
      "summary": "2018 AFCEA TechNet Asia-Pacific Conference",
      "highlights": [
        "Attended Women in AFCEA Panel",
        "Volunteered at Registration"
      ]
    },
    {
      "organization": "Engineer's Council at the University of Hawaii",
      "website": "",
      "position": "Volunteer",
      "startDate": "2018-11-02",
      "endDate": "2017-11-03",
      "summary": "2018 ECUH VEX Tournament",
      "highlights": [
        "Helped build stages and props",
        "Volunteered as Pit Manager"
      ]
    },
    
  ],
  "awards": [
    {
      "title": "Natural Science Foundation Bridges to Baccalaureate: Strategic Alliance for Minority Participation Award",
      "date": "Fall 2018 Semester",
      "awarder": "Kapiolani Community College",
      "summary": "The NSF B2B STAMP Award program supports and advances STEM Education and transfer of Native Hawaiian and Underrepresented Minority students into a baccalaureate STEM degree."
    },
    {
      "title": "Best Entertainment/Gaming App: 1st Place",
      "date": "March 21018",
      "awarder": "AT&T Hackathon 2018",
      "summary": "Our team, Team Turretz, won first place. I gained experience in Unity and C# to program a VR game for the Microsoft HoloLens.",
      "website": "https://bit.ly/2n01c8n"
    }
  ],
  "references": [
    {
      "name": "Keomailani Eaton",
      "reference": "STEM Center Coordinator at Kapiolani Community College"
    }
  ]
}
